pyjo_mdl/__init__.py
pyjo_mdl/core.py
pyjo_mdl/exceptions.py
pyjo_mdl/helpers.py
pyjo_mdl/model_classes.py
pyjo_mdl-0.1.4.dist-info/METADATA
pyjo_mdl-0.1.4.dist-info/RECORD
pyjo_mdl-0.1.4.dist-info/WHEEL
pyjo_mdl-0.1.4.dist-info/top_level.txt
