Metadata-Version: 2.1
Name: pyjo-mdl
Version: 0.1.4
Summary: Model Definition Language for Pyjo
Home-page: https://github.com/xelhark/pyjo-mdl
Author: Gabriele Platania
Author-email: gabriele.platania@gmail.com
License: UNKNOWN
Platform: UNKNOWN
Requires-Dist: pyjo
